LICENSE.txt
README.txt
setup.py
Oasys_Widget_Core.egg-info/PKG-INFO
Oasys_Widget_Core.egg-info/SOURCES.txt
Oasys_Widget_Core.egg-info/dependency_links.txt
Oasys_Widget_Core.egg-info/requires.txt
Oasys_Widget_Core.egg-info/top_level.txt
orangewidget/__init__.py
orangewidget/gui.py
orangewidget/settings.py
orangewidget/widget.py
orangewidget/canvas/__init__.py
orangewidget/canvas/config.py
orangewidget/canvas/discovery.py
orangewidget/canvas/workflow.py
orangewidget/icons/Dlg_arrow.png
orangewidget/icons/Dlg_clear.png
orangewidget/icons/Dlg_down3.png
orangewidget/icons/Dlg_enter.png
orangewidget/icons/Dlg_pan_hand.png
orangewidget/icons/Dlg_redo.png
orangewidget/icons/Dlg_send.png
orangewidget/icons/Dlg_sort.png
orangewidget/icons/Dlg_undo.png
orangewidget/icons/Dlg_up3.png
orangewidget/icons/Dlg_zoom.png
orangewidget/icons/Dlg_zoom_reset.png
orangewidget/icons/Dlg_zoom_selection.png
orangewidget/icons/Unknown.png
orangewidget/icons/downgreenarrow.png
orangewidget/icons/error.png
orangewidget/icons/information.png
orangewidget/icons/upgreenarrow.png
orangewidget/icons/warning.png